edge/__init__.py
edge/cli.py
edge/django.py
django_edge-0.0.1.dist-info/METADATA
django_edge-0.0.1.dist-info/WHEEL
django_edge-0.0.1.dist-info/entry_points.txt
django_edge-0.0.1.dist-info/top_level.txt
django_edge-0.0.1.dist-info/RECORD
